checkbrocade/README.md
checkbrocade/__init__.py
checkbrocade/cli.py
checkbrocade/nix
checkbrocade/poc.py
checkbrocade/brocadecmd/__init__.py
checkbrocade/brocadecmd/about.py
checkbrocade/brocadecmd/eport.py
checkbrocade/brocadecmd/hardwarehealth.py
checkbrocade/brocadecmd/interfacehealth.py
checkbrocade/tools/__init__.py
checkbrocade/tools/cli.py
checkbrocade/tools/connect.py
checkbrocade/tools/helper.py
checkbrocade-0.1a2.dist-info/entry_points.txt
checkbrocade-0.1a2.dist-info/WHEEL
checkbrocade-0.1a2.dist-info/METADATA
checkbrocade-0.1a2.dist-info/RECORD
