Metadata-Version: 2.1
Name: checkbrocade
Version: 0.1a2
Summary: check_brocade monitoring plugin
Author-email: Matthias Gallinger <matthias.gallinger@consol.de>
Requires-Python: >= 3.6
Classifier: Development Status :: 3 - Alpha
Classifier: Topic :: System :: Monitoring
Classifier: License :: OSI Approved :: GNU Affero General Public License v3 or later (AGPLv3+)
Requires-Dist: monplugin >= 0.6.2
Project-URL: homepage, https://github.com/consol/check_brocade
Project-URL: issues, https://github.com/consol/check_brocade/issues
Project-URL: repository, https://github.com/consol/check_brocade.git
